[{"line":2,"elements":[{"line":4,"name":"","description":"","type":"background","keyword":"Background","steps":[{"result":{"duration":1024664900,"status":"passed"},"line":5,"name":"User is logged in successfully","match":{"location":"web.LoginSteps.user_logged_in_successfully()"},"keyword":"Given "}]},{"start_timestamp":"2026-02-24T05:51:29.258Z","before":[{"result":{"duration":1382716500,"status":"passed"},"match":{"location":"hooks.WebHooks.setup()"}}],"line":7,"name":"Add product to cart","description":"","id":"inventory-functionality;add-product-to-cart","after":[{"result":{"duration":168858200,"status":"passed"},"match":{"location":"hooks.WebHooks.tearDown()"}}],"type":"scenario","keyword":"Scenario","steps":[{"result":{"duration":97908800,"status":"passed"},"line":8,"name":"User adds \"Sauce Labs Backpack\" to cart","match":{"arguments":[{"val":"\"Sauce Labs Backpack\"","offset":10}],"location":"web.InventorySteps.user_adds_product_to_cart(java.lang.String)"},"keyword":"When "},{"result":{"duration":19293800,"status":"passed"},"line":9,"name":"Cart badge should show 1 item","match":{"location":"web.InventorySteps.cart_badge_should_show_1_item()"},"keyword":"Then "}],"tags":[{"name":"@web"}]},{"line":4,"name":"","description":"","type":"background","keyword":"Background","steps":[{"result":{"duration":793996300,"status":"passed"},"line":5,"name":"User is logged in successfully","match":{"location":"web.LoginSteps.user_logged_in_successfully()"},"keyword":"Given "}]},{"start_timestamp":"2026-02-24T05:51:31.976Z","before":[{"result":{"duration":698261300,"status":"passed"},"match":{"location":"hooks.WebHooks.setup()"}}],"line":11,"name":"Filter product by price low to high","description":"","id":"inventory-functionality;filter-product-by-price-low-to-high","after":[{"result":{"duration":152942500,"status":"passed"},"match":{"location":"hooks.WebHooks.tearDown()"}}],"type":"scenario","keyword":"Scenario","steps":[{"result":{"duration":102706800,"status":"passed"},"line":12,"name":"User selects filter \"Price (low to high)\"","match":{"arguments":[{"val":"\"Price (low to high)\"","offset":20}],"location":"web.InventorySteps.user_selects_filter(java.lang.String)"},"keyword":"When "},{"result":{"duration":92583100,"status":"passed"},"line":13,"name":"Products should be sorted by lowest price first","match":{"location":"web.InventorySteps.verify_sorted_by_price()"},"keyword":"Then "}],"tags":[{"name":"@web"}]},{"line":4,"name":"","description":"","type":"background","keyword":"Background","steps":[{"result":{"duration":825585700,"status":"passed"},"line":5,"name":"User is logged in successfully","match":{"location":"web.LoginSteps.user_logged_in_successfully()"},"keyword":"Given "}]},{"start_timestamp":"2026-02-24T05:51:33.824Z","before":[{"result":{"duration":688888800,"status":"passed"},"match":{"location":"hooks.WebHooks.setup()"}}],"line":15,"name":"Filter product by name Z to A","description":"","id":"inventory-functionality;filter-product-by-name-z-to-a","after":[{"result":{"duration":125114500,"status":"passed"},"match":{"location":"hooks.WebHooks.tearDown()"}}],"type":"scenario","keyword":"Scenario","steps":[{"result":{"duration":89284700,"status":"passed"},"line":16,"name":"User selects filter \"Name (Z to A)\"","match":{"arguments":[{"val":"\"Name (Z to A)\"","offset":20}],"location":"web.InventorySteps.user_selects_filter(java.lang.String)"},"keyword":"When "},{"result":{"duration":58279000,"status":"passed"},"line":17,"name":"Products should be sorted in descending order","match":{"location":"web.InventorySteps.verify_sorted_by_name_desc()"},"keyword":"Then "}],"tags":[{"name":"@web"}]},{"line":4,"name":"","description":"","type":"background","keyword":"Background","steps":[{"result":{"duration":796546300,"status":"passed"},"line":5,"name":"User is logged in successfully","match":{"location":"web.LoginSteps.user_logged_in_successfully()"},"keyword":"Given "}]},{"start_timestamp":"2026-02-24T05:51:35.615Z","before":[{"result":{"duration":684481800,"status":"passed"},"match":{"location":"hooks.WebHooks.setup()"}}],"line":19,"name":"User Logout","description":"","id":"inventory-functionality;user-logout","after":[{"result":{"duration":127916000,"status":"passed"},"match":{"location":"hooks.WebHooks.tearDown()"}}],"type":"scenario","keyword":"Scenario","steps":[{"result":{"duration":698336200,"status":"passed"},"line":20,"name":"User logs out from application","match":{"location":"web.InventorySteps.user_logs_out()"},"keyword":"When "},{"result":{"duration":5421700,"status":"passed"},"line":21,"name":"User should be redirected to login page","match":{"location":"web.InventorySteps.redirected_to_login_page()"},"keyword":"Then "}],"tags":[{"name":"@web"}]}],"name":"Inventory functionality","description":"","id":"inventory-functionality","keyword":"Feature","uri":"classpath:web/Inventory.feature","tags":[{"name":"@web","type":"Tag","location":{"line":1,"column":1}}]},{"line":2,"elements":[{"start_timestamp":"2026-02-24T05:51:37.936Z","before":[{"result":{"duration":742048600,"status":"passed"},"match":{"location":"hooks.WebHooks.setup()"}}],"line":4,"name":"Successful login with valid credentials","description":"","id":"login;successful-login-with-valid-credentials","after":[{"result":{"duration":157023200,"status":"passed"},"match":{"location":"hooks.WebHooks.tearDown()"}}],"type":"scenario","keyword":"Scenario","steps":[{"result":{"duration":563621900,"status":"passed"},"line":5,"name":"User is on login page","match":{"location":"web.LoginSteps.user_is_on_login_page()"},"keyword":"Given "},{"result":{"duration":157069200,"status":"passed"},"line":6,"name":"User enters valid username and password","match":{"location":"web.LoginSteps.user_enters_valid_credentials()"},"keyword":"When "},{"result":{"duration":87144500,"status":"passed"},"line":7,"name":"User clicks login button","match":{"location":"web.LoginSteps.user_clicks_login_button()"},"keyword":"And "},{"result":{"duration":5010200,"status":"passed"},"line":8,"name":"User should be redirected to homepage","match":{"location":"web.LoginSteps.user_redirected_homepage()"},"keyword":"Then "}],"tags":[{"name":"@web"}]},{"start_timestamp":"2026-02-24T05:51:39.655Z","before":[{"result":{"duration":679306200,"status":"passed"},"match":{"location":"hooks.WebHooks.setup()"}}],"line":10,"name":"Failed login with invalid credentials","description":"","id":"login;failed-login-with-invalid-credentials","after":[{"result":{"duration":126948400,"status":"passed"},"match":{"location":"hooks.WebHooks.tearDown()"}}],"type":"scenario","keyword":"Scenario","steps":[{"result":{"duration":439720400,"status":"passed"},"line":11,"name":"User is on login page","match":{"location":"web.LoginSteps.user_is_on_login_page()"},"keyword":"Given "},{"result":{"duration":174701400,"status":"passed"},"line":12,"name":"User enters invalid username and password","match":{"location":"web.LoginSteps.user_enters_invalid_credentials()"},"keyword":"When "},{"result":{"duration":91421500,"status":"passed"},"line":13,"name":"User clicks login button","match":{"location":"web.LoginSteps.user_clicks_login_button()"},"keyword":"And "},{"result":{"duration":22367200,"status":"passed"},"line":14,"name":"Error message should be displayed","match":{"location":"web.LoginSteps.error_message_displayed()"},"keyword":"Then "}],"tags":[{"name":"@web"}]}],"name":"Login","description":"","id":"login","keyword":"Feature","uri":"classpath:web/login.feature","tags":[{"name":"@web","type":"Tag","location":{"line":1,"column":1}}]}]